{
    "nodes": [
        {
            "type": "PARAGRAPH",
            "id": "17btipMjl",
            "nodes": [
                {
                    "type": "TEXT",
                    "id": "node-1",
                    "textData": {
                        "text": "Bold ",
                        "decorations": [
                            {
                                "type": "BOLD",
                                "fontWeightValue": 700
                            }
                        ]
                    }
                }
            ]
        },
        {
            "type": "PARAGRAPH",
            "id": "Tv01a176y",
            "nodes": [
                {
                    "type": "TEXT",
                    "id": "node-2",
                    "textData": {
                        "text": "Italic ",
                        "decorations": [
                            {
                                "type": "ITALIC",
                                "italicData": false
                            }
                        ]
                    }
                }
            ]
        },
        {
            "type": "PARAGRAPH",
            "id": "0djdvaPrr",
            "nodes": [
                {
                    "type": "TEXT",
                    "id": "node-3",
                    "textData": {
                        "text": "Underlined ",
                        "decorations": [
                            {
                                "type": "UNDERLINE",
                                "underlineData": true
                            }
                        ]
                    }
                }
            ]
        },
        {
            "type": "PARAGRAPH",
            "id": "HJociQWH8",
            "nodes": [
                {
                    "type": "TEXT",
                    "id": "node-4",
                    "textData": {
                        "text": "Spoiler ",
                        "decorations": [
                            {
                                "type": "SPOILER"
                            }
                        ]
                    }
                }
            ]
        },
        {
            "type": "PARAGRAPH",
            "id": "YV2qi4NW4",
            "nodes": [
                {
                    "type": "TEXT",
                    "id": "node-5",
                    "textData": {
                        "text": "Anchor ",
                        "decorations": [
                            {
                                "type": "ANCHOR",
                                "anchorData": {
                                    "anchor": "rppfEuOzn"
                                }
                            }
                        ]
                    }
                }
            ]
        },
        {
            "type": "PARAGRAPH",
            "id": "2Q4gwCpuc",
            "nodes": [
                {
                    "type": "TEXT",
                    "id": "node-6",
                    "textData": {
                        "text": "@JonhDoe ",
                        "decorations": [
                            {
                                "type": "MENTION",
                                "mentionData": {
                                    "name": "John Doe",
                                    "slug": "johndoe",
                                    "id": "user123"
                                }
                            }
                        ]
                    }
                }
            ]
        },
        {
            "type": "TEXT",
            "id": "",
            "textData": {
                "text": "Link ",
                "decorations": [
                    {
                        "type": "LINK",
                        "linkData": {
                            "link": {
                                "url": "https://en.wikipedia.org/wiki/Quinoa",
                                "target": "BLANK",
                                "rel": {
                                    "noreferrer": true
                                }
                            }
                        }
                    },
                    {
                        "type": "UNDERLINE"
                    }
                ]
            }
        },
        {
            "type": "PARAGRAPH",
            "id": "rppfEuOzn",
            "nodes": [
                {
                    "type": "TEXT",
                    "id": "node-8",
                    "textData": {
                        "text": "Color ",
                        "decorations": [
                            {
                                "type": "COLOR",
                                "colorData": {
                                    "background": "#C0C0C0",
                                    "foreground": "#FF5733"
                                }
                            }
                        ]
                    }
                }
            ]
        },
        {
            "type": "PARAGRAPH",
            "id": "afvmlcpWj",
            "nodes": [
                {
                    "type": "TEXT",
                    "id": "node-9",
                    "textData": {
                        "text": "Font Size ",
                        "decorations": [
                            {
                                "type": "FONT_SIZE",
                                "fontSizeData": {
                                    "unit": "PX",
                                    "value": 24
                                }
                            }
                        ]
                    }
                }
            ]
        },
        {
            "type": "PARAGRAPH",
            "id": "y549n1",
            "nodes": [
                {
                    "type": "TEXT",
                    "textData": {
                        "text": "Text with multiple decorations",
                        "decorations": [
                            {
                                "type": "BOLD",
                                "fontWeightValue": 700
                            },
                            {
                                "type": "COLOR",
                                "colorData": {
                                    "background": "#BFAD80",
                                    "foreground": "#0141AA"
                                }
                            },
                            {
                                "type": "ITALIC",
                                "italicData": true
                            },
                            {
                                "type": "UNDERLINE"
                            }
                        ]
                    }
                }
            ]
        }
    ]
}